sdtm_mapper/SDTMMapper.py
sdtm_mapper/SDTMModels.py
sdtm_mapper/__init__.py
sdtm_mapper/elmolayer.py
sdtm_mapper/samples.py
sdtm_mapper/data/ae_test_study.csv
sdtm_mapper/decode/test_encode.pkl
sdtm_mapper/decode/train_encode.pkl
sdtm_mapper/decode/valid_encode.pkl
sdtm_mapper/models/Elmo+fnn+ae+Model2.h5
sdtm_mapper/models/Elmo+fnn+ae+Model3.h5
sdtm_mapper/models/Elmo+sfnn+ae+Model1.h5
sdtm_mapper-0.3.8.dist-info/LICENSE
sdtm_mapper-0.3.8.dist-info/METADATA
sdtm_mapper-0.3.8.dist-info/WHEEL
sdtm_mapper-0.3.8.dist-info/top_level.txt
sdtm_mapper-0.3.8.dist-info/RECORD
