Metadata-Version: 2.1
Name: sdtm-mapper
Version: 0.3.8
Summary: CDISC SDTM Mapping Tool
Home-page: https://github.com/stomioka/sdtm_mapper
Author: Sam Tomioka
Author-email: stomioka@gmail.com
License: LICENSE
Keywords: SDTM,CDISC,SAS,SAS7BDAT
Platform: UNKNOWN
Classifier: Programming Language :: Python :: 3.6
Classifier: License :: OSI Approved :: MIT License
Classifier: Natural Language :: English
Classifier: Topic :: Scientific/Engineering :: Artificial Intelligence
Requires-Dist: numpy
Requires-Dist: pandas
Requires-Dist: pathlib
Requires-Dist: sas7bdat
Requires-Dist: boto3
Requires-Dist: botocore
Requires-Dist: sklearn
Requires-Dist: keras
